jkdownload/__init__.py
jkdownload/__main__.py
jkdownload/jkdownload.py
jkdownload-0.0.3.dist-info/entry_points.txt
jkdownload-0.0.3.dist-info/LICENSE
jkdownload-0.0.3.dist-info/WHEEL
jkdownload-0.0.3.dist-info/METADATA
jkdownload-0.0.3.dist-info/RECORD
